manaflow/__init__.py
manaflow/connection.py
manaflow/secrets.py
manaflow-0.1.0.dist-info/licenses/LICENSE
manaflow-0.1.0.dist-info/METADATA
manaflow-0.1.0.dist-info/WHEEL
manaflow-0.1.0.dist-info/top_level.txt
manaflow-0.1.0.dist-info/RECORD
