Metadata-Version: 2.4
Name: manaflow
Version: 0.1.0
Summary: Async connection management for Manaflow services
Home-page: https://github.com/lawrencecchen/autobuild11
Author: Manaflow
Author-email: info@manaflow.ai
Classifier: Programming Language :: Python :: 3
Classifier: License :: OSI Approved :: MIT License
Classifier: Operating System :: OS Independent
Requires-Python: >=3.7
License-File: LICENSE
Dynamic: author
Dynamic: author-email
Dynamic: classifier
Dynamic: description
Dynamic: description-content-type
Dynamic: home-page
Dynamic: license-file
Dynamic: requires-python
Dynamic: summary
